sealeveltools/__init__.py
sealeveltools/sl_class.py
sealeveltools/sl_plots.py
sealeveltools/sl_stats.py
sealeveltools/sl_utils.py
sealeveltools/version.py
sealeveltools-0.0.0.dist-info/LICENCE
sealeveltools-0.0.0.dist-info/METADATA
sealeveltools-0.0.0.dist-info/WHEEL
sealeveltools-0.0.0.dist-info/top_level.txt
sealeveltools-0.0.0.dist-info/RECORD
